BlackDuckUtils/BlackDuckOutput.py
BlackDuckUtils/MavenUtils.py
BlackDuckUtils/NpmUtils.py
BlackDuckUtils/Utils.py
BlackDuckUtils/bdio.py
BlackDuckUtils/globals.py
blackduck_python_utils-0.1.3.dist-info/LICENSE
blackduck_python_utils-0.1.3.dist-info/METADATA
blackduck_python_utils-0.1.3.dist-info/WHEEL
blackduck_python_utils-0.1.3.dist-info/top_level.txt
blackduck_python_utils-0.1.3.dist-info/RECORD
