Metadata-Version: 2.1
Name: blackduck-python-utils
Version: 0.1.3
Summary: Python wrapper for common patterns used with Black Duck.
Home-page: https://github.com/synopsys-sig-community/BlackDuckUtils
Author: James Croall
Author-email: jcroall@synopsys.com
License: Apache
Platform: UNKNOWN
Classifier: Programming Language :: Python :: 3
Classifier: License :: OSI Approved :: Apache Software License
Classifier: Operating System :: OS Independent
Requires-Dist: blackduck
Requires-Dist: networkx
